breezo/__init__.py
breezo/client.py
breezo-1.0.14.dist-info/LICENSE.txt
breezo-1.0.14.dist-info/METADATA
breezo-1.0.14.dist-info/WHEEL
breezo-1.0.14.dist-info/top_level.txt
breezo-1.0.14.dist-info/RECORD
