Metadata-Version: 2.1
Name: breezo
Version: 1.0.14
Summary: Python package for dynamic centralized configuration manager for microservices
Home-page: https://github.com/nimesh-mittal/breezo-sdk
Author: nimeshmittal
Author-email: nimesh.mittal@gmail.com
License: UNKNOWN
Platform: UNKNOWN
Requires-Dist: requests
